minica_api_pihole/main.py
minica_api_pihole_client-0.3.0.dist-info/entry_points.txt
minica_api_pihole_client-0.3.0.dist-info/LICENSE.md
minica_api_pihole_client-0.3.0.dist-info/WHEEL
minica_api_pihole_client-0.3.0.dist-info/METADATA
minica_api_pihole_client-0.3.0.dist-info/RECORD
